gemini_terminal/__init__.py
gemini_terminal/main.py
gemini_terminal-0.1.7.dist-info/LICENSE
gemini_terminal-0.1.7.dist-info/METADATA
gemini_terminal-0.1.7.dist-info/WHEEL
gemini_terminal-0.1.7.dist-info/entry_points.txt
gemini_terminal-0.1.7.dist-info/top_level.txt
gemini_terminal-0.1.7.dist-info/RECORD
