Metadata-Version: 2.1
Name: gemini-terminal
Version: 0.1.7
Summary: A terminal-based chat interface for Google's Gemini AI
Author: Your Name
Author-email: your.email@example.com
License-File: LICENSE
Requires-Dist: google-generativeai
Requires-Dist: pyperclip
